LICENSE
tw_complex/__init__.py
tw_complex/cdist_brute.py
tw_complex/cdist_knn.py
tw_complex-1.1.0.dist-info/LICENSE
tw_complex-1.1.0.dist-info/WHEEL
tw_complex-1.1.0.dist-info/METADATA
tw_complex-1.1.0.dist-info/RECORD
