Metadata-Version: 2.1
Name: tw-complex
Version: 1.1.0
Summary: Algorithms for TW
Home-page: https://github.com/rafsaf/tw-complex
License: MIT
Keywords: Python,Tribal Wars
Author: rafsaf
Author-email: rafal.safin12@gmail.com
Requires-Python: >=3.8,<3.12
Classifier: License :: OSI Approved :: MIT License
Classifier: Programming Language :: Python :: 3
Classifier: Programming Language :: Python :: 3.8
Classifier: Programming Language :: Python :: 3.9
Classifier: Programming Language :: Python :: 3.10
Classifier: Programming Language :: Python :: 3.11
Requires-Dist: numpy (>=1.23.4,<2.0.0)
Requires-Dist: scikit-learn (>=1.1.3,<2.0.0)
Requires-Dist: scipy (>=1.9.3,<2.0.0)
Project-URL: Repository, https://github.com/rafsaf/tw-complex
